<?xml version="1.0" encoding="UTF-8"?>
<objects serializationModel="Studio.02.02.00">
	<object class="AudioFile" id="{44952a1d-f593-4862-9193-7551fc9770db}">
		<property name="assetPath">
			<value>shs_oat_birds_chirp_forest_hills_countryside_Transylvania_7.wav</value>
		</property>
		<property name="isStreaming">
			<value>true</value>
		</property>
		<property name="frequencyInKHz">
			<value>44.0999985</value>
		</property>
		<property name="channelCount">
			<value>2</value>
		</property>
		<property name="length">
			<value>80.584376417233557</value>
		</property>
		<relationship name="masterAssetFolder">
			<destination>{173563f8-6aeb-4e7d-be22-08f5fdcf7c41}</destination>
		</relationship>
	</object>
</objects>
